logger.py
mongo_client_gateway.py
utils.py
atxciccgateway/__init__.py
atxciccgateway/atx_server.py
atxciccgateway/atx_tool.py
atxciccgateway/constants.py
atxciccgateway/logger.py
atxciccgateway/utils.py
cats_gateway/__init__.py
cats_gateway/cats_server.py
cats_gateway/cats_tool.py
cats_gateway/constants.py
cats_gateway/utils.py
cats_uni_gateway/__init__.py
cats_uni_gateway/cats_server.py
cats_uni_gateway/cats_tool.py
cats_uni_gateway/constants.py
cats_uni_gateway/utils.py
emc_gateway/__init__.py
emc_gateway/constants.py
emc_gateway/emc_server.py
emc_gateway/emc_tool.py
emc_gateway/utils.py
gd_kfgateway/__init__.py
gd_kfgateway/constants.py
gd_kfgateway/kf_server.py
gd_kfgateway/kf_tool.py
gd_kfgateway/logger.py
gd_kfgateway/utils.py
gf_tytgateway/__init__.py
gf_tytgateway/constants.py
gf_tytgateway/gf_server.py
gf_tytgateway/gf_tool.py
gf_tytgateway/utils.py
hx_kfgateway/__init__.py
hx_kfgateway/constants.py
hx_kfgateway/kf_server.py
hx_kfgateway/kf_tool.py
hx_kfgateway/logger.py
hx_kfgateway/utils.py
ims_gateway/__init__.py
ims_gateway/constants.py
ims_gateway/ims_server.py
ims_gateway/ims_tool.py
ims_gateway/logger.py
ims_gateway/mongo_client_gateway.py
ims_gateway/utils.py
matics_quant/__init__.py
matics_quant/constants.py
matics_quant/matic_client.py
matics_quant/matic_server.py
matics_quant/mquant_tool.py
matics_quant/order_msg.py
matics_quant/string_buffer.py
matics_quant/tcp_server.py
matics_quant/trade_data_dump.py
matics_quant/utils.py
pyatxgateway/__init__.py
pyatxgateway/atx_server.py
pyatxgateway/atx_tool.py
pyatxgateway/constants.py
pyatxgateway/logger.py
pyatxgateway/utils.py
pytlgateway/__init__.py
pytlgateway/constants.py
pytlgateway/ft_server.py
pytlgateway/ft_tool.py
pytlgateway/logger.py
pytlgateway/utils.py
zghs_atxgateway/__init__.py
zghs_atxgateway/atx_server.py
zghs_atxgateway/atx_tool.py
zghs_atxgateway/constants.py
zghs_atxgateway/logger.py
zghs_atxgateway/utils.py
zs_atx_gateway/__init__.py
zs_atx_gateway/atx_server.py
pytlgateway-0.2.46.dist-info/METADATA
pytlgateway-0.2.46.dist-info/WHEEL
pytlgateway-0.2.46.dist-info/top_level.txt
pytlgateway-0.2.46.dist-info/RECORD
